pipcreator/__init__.py
pipcreator/color.py
pipcreator/constants.py
pipcreator/convert.py
pipcreator/createtest.py
pipcreator/guide.py
pipcreator/main.py
pipcreator/upload.py
pipcreator/writer.py
pipCreator-0.1.0.dist-info/LICENSE
pipCreator-0.1.0.dist-info/METADATA
pipCreator-0.1.0.dist-info/WHEEL
pipCreator-0.1.0.dist-info/entry_points.txt
pipCreator-0.1.0.dist-info/top_level.txt
pipCreator-0.1.0.dist-info/RECORD
