Metadata-Version: 2.1
Name: pipCreator
Version: 0.1.0
Summary: This creates all the necessary files for creating a python package.
Home-page: https://github.com/rakeshkanna-rk/pipCreator
Author: Rakesh Kanna
Author-email: rakeshkanna0108@gmail.com
License: MIT
Project-URL: GitHub, https://github.com/rakeshkanna-rk/pipCreator/
Project-URL: PyPI, https://pypi.org/project/pipCreator/
Keywords: pip,package,python,setup,create,creator
Classifier: Programming Language :: Python :: 3
Classifier: License :: OSI Approved :: MIT License
Classifier: Operating System :: OS Independent
Requires-Python: >=3.6
License-File: LICENSE
Requires-Dist: click
Requires-Dist: colorama
Requires-Dist: twine
Requires-Dist: setuptools
Requires-Dist: wheel
